ezgpx/__init__.py
ezgpx/gpx/__init__.py
ezgpx/gpx/gpx.py
ezgpx/gpx_elements/__init__.py
ezgpx/gpx_elements/bounds.py
ezgpx/gpx_elements/copyright.py
ezgpx/gpx_elements/email.py
ezgpx/gpx_elements/extensions.py
ezgpx/gpx_elements/gpx.py
ezgpx/gpx_elements/gpx_element.py
ezgpx/gpx_elements/link.py
ezgpx/gpx_elements/metadata.py
ezgpx/gpx_elements/person.py
ezgpx/gpx_elements/point.py
ezgpx/gpx_elements/point_segment.py
ezgpx/gpx_elements/route.py
ezgpx/gpx_elements/track.py
ezgpx/gpx_elements/track_segment.py
ezgpx/gpx_elements/way_point.py
ezgpx/parsers/__init__.py
ezgpx/parsers/fit_parser.py
ezgpx/parsers/gpx_parser.py
ezgpx/parsers/kml_parser.py
ezgpx/parsers/parser.py
ezgpx/parsers/xml_parser.py
ezgpx/plotters/__init__.py
ezgpx/plotters/folium_plotter.py
ezgpx/plotters/gmplot_plotter.py
ezgpx/plotters/matplotlib_anim_plotter.py
ezgpx/plotters/matplotlib_plotter.py
ezgpx/plotters/plotly_anim_plotter.py
ezgpx/plotters/plotly_plotter.py
ezgpx/plotters/plotter.py
ezgpx/schemas/__init__.py
ezgpx/schemas/gpx_1_0/gpx.xsd
ezgpx/schemas/gpx_1_1/gpx.xsd
ezgpx/schemas/kml_2_2/atom-author-link.xsd
ezgpx/schemas/kml_2_2/ogckml22.xsd
ezgpx/schemas/kml_2_2/xAL.xsd
ezgpx/utils/__init__.py
ezgpx/utils/algorithms.py
ezgpx/utils/distance.py
ezgpx/writers/__init__.py
ezgpx/writers/gpx_writer.py
ezgpx/writers/gpx_writer_method_behavior_creator.py
ezgpx/writers/kml_writer.py
ezgpx/writers/writer.py
ezgpx-0.3.0.dist-info/licenses/LICENSE
ezgpx-0.3.0.dist-info/METADATA
ezgpx-0.3.0.dist-info/WHEEL
ezgpx-0.3.0.dist-info/top_level.txt
ezgpx-0.3.0.dist-info/RECORD
