Metadata-Version: 2.4
Name: ezgpx
Version: 0.3.0
Summary: Easy to use Python GPX library
Author-email: Fabien ALLEMAND <allemand.fabien@orange.fr>
Maintainer-email: Fabien ALLEMAND <allemand.fabien@orange.fr>
License: GNU GPLv3
Project-URL: Documentation, https://ezgpx.readthedocs.io/en/latest/
Project-URL: Repository, https://github.com/FABallemand/ezGPX
Project-URL: Issues, https://github.com/FABallemand/ezGPX/issues
Project-URL: PyPi, https://pypi.org/project/ezgpx/
Keywords: gpx,gpx-files,gpx-parser,gpx-reader,gpx-writer,gpx-converter,gpx-data,kml,kmz,fit
Classifier: Intended Audience :: Developers
Classifier: Programming Language :: Python
Classifier: Programming Language :: Python :: 3
Classifier: Programming Language :: Python :: 3.9
Classifier: Programming Language :: Python :: 3.10
Classifier: Programming Language :: Python :: 3.11
Classifier: Programming Language :: Python :: 3.12
Classifier: Operating System :: OS Independent
Requires-Python: >=3.9
License-File: LICENSE
Requires-Dist: lxml
Requires-Dist: xmlschema
Requires-Dist: importlib_resources
Requires-Dist: python-dateutil
Requires-Dist: pandas
Requires-Dist: polars
Requires-Dist: matplotlib
Requires-Dist: basemap
Requires-Dist: plotly
Requires-Dist: gmplot
Requires-Dist: folium
Requires-Dist: fitparse
Requires-Dist: pytest
Dynamic: license-file
